{
  "distributor_code": "10310151",
  "property_name": "Prueba 3",
  "store_id_ERP": "",
  "Store_Status": 2,
  "rejection_reason": "CC",
  "erp_seller": "",
  "cuit_dni_id": "23520085",
  "document_type_id": "2",
  "ingresos_brutos": "",
  "customer_type": "",
  "street": "San Martin",
  "number": "600",
  "Neighborhood": "Ciudadela",
  "District": "Tres de Febrero",
  "Province": "Buenos Aires",
  "country": "Argentina",
  "postal_code": "B1702DWL",
  "phone_number": "+54 9 11 3116 5754",
  "mobile_number": "+54 9 15 3116 5754",
  "email": "pepeprueba@gmail.com",
  "firstname": "Pepe",
  "surname": "Prueba",
  "customer_credit_available": 0.0,
  "customer_total_credit": 0.0,
  "customer_pending_payment": 0.0
}